getownip/__init__.py
getownip-0.0.5.dist-info/METADATA
getownip-0.0.5.dist-info/WHEEL
getownip-0.0.5.dist-info/licenses/LICENSE
getownip-0.0.5.dist-info/RECORD
