Metadata-Version: 2.1
Name: getownip
Version: 0.0.5
Summary: Get your own ip address
Project-URL: Homepage, https://gitlab.com/lfuerderer1/getownip
Author-email: Lukas Fürderer <l.fuerderer@gmail.com>
License-File: LICENSE
Classifier: License :: OSI Approved :: MIT License
Classifier: Operating System :: OS Independent
Classifier: Programming Language :: Python :: 3
Requires-Python: >=3.5
